tangerine/VERSION
tangerine/__init__.py
tangerine/client.py
tangerine/exceptions.py
tangerine/login.py
tangerine/secret_provider.py
tangerine-0.3.9.dist-info/DESCRIPTION.rst
tangerine-0.3.9.dist-info/METADATA
tangerine-0.3.9.dist-info/RECORD
tangerine-0.3.9.dist-info/WHEEL
tangerine-0.3.9.dist-info/metadata.json
tangerine-0.3.9.dist-info/top_level.txt
