Metadata-Version: 2.0
Name: tangerine
Version: 0.3.9
Summary: API for the Tangerine Bank
Home-page: https://github.com/kevinjqiu/tangerine
Author: Kevin J. Qiu
Author-email: kevin@idempotent.ca
License: UNKNOWN
Platform: UNKNOWN
Classifier: Development Status :: 2 - Pre-Alpha
Classifier: Programming Language :: Python
Classifier: Programming Language :: Python :: 3
Classifier: Programming Language :: Python :: 3.4
Classifier: Programming Language :: Python :: 3.5
Requires-Dist: certifi (==2017.11.5)
Requires-Dist: chardet (==3.0.4)
Requires-Dist: idna (==2.6)
Requires-Dist: requests (==2.18.4)
Requires-Dist: urllib3 (==1.22)
